<?xml version="1.0" encoding="UTF-8"?>
<MF0 version="1.1" packageUris="http://schema.mathworks.com/mf0/sl_modelref_info/R2020a http://schema.mathworks.com/mf0/slexec_mm_sto/R2019b_201902271317">
  <ModelRefInfoRepo.ModelRefInfoRoot type="ModelRefInfoRepo.ModelRefInfoRoot" uuid="14124e27-1b87-450b-867e-5a7710dec330">
    <autoSolverStatusFlags>335</autoSolverStatusFlags>
    <childModelRefInfo type="ModelRefInfoRepo.ChildModelRefInfo" uuid="b265e79a-b4ce-4c16-86d7-b74c70a5961a">
      <modelName>ARM_model_2020a</modelName>
      <modelPath>ARM_model_2020a</modelPath>
    </childModelRefInfo>
    <dataTransferInfos>AAFJTQAAAAAOAAAAOAAAAAYAAAAIAAAAAgAAAAAAAAAFAAAACAAAAAAAAAABAAAAAQAAAAAAAAAFAAQAAQAAAAEAAAAAAAAA</dataTransferInfos>
    <fundamentalSampleTimePeriod>0.20000000000000001</fundamentalSampleTimePeriod>
    <hasBlockWithPeriodicDiscreteSampleTime>true</hasBlockWithPeriodicDiscreteSampleTime>
    <hasBwsAccessed>true</hasBwsAccessed>
    <hasBwsAccessedByAnyModel>true</hasBwsAccessedByAnyModel>
    <isInlineParamsOn>true</isInlineParamsOn>
    <loggingSaveFormat>6</loggingSaveFormat>
    <maxFreqHz>-1</maxFreqHz>
    <runtimeNonFcnCallRateInfos type="ModelRefInfoRepo.RateInfo">
      <compiled>true</compiled>
      <nonFcnCallPartitionName>D1</nonFcnCallPartitionName>
      <period>0.20000000000000001</period>
      <priority>40</priority>
      <rateIdx>0</rateIdx>
    </runtimeNonFcnCallRateInfos>
    <sampleTimeInheritanceRule>1</sampleTimeInheritanceRule>
    <timingAndTaskingRegistry>&lt;?xml version=&quot;1.0&quot;?&gt;
&lt;slexec_sto version=&quot;1.1&quot; packageUris=&quot;http://schema.mathworks.com/mf0/slexec_mm_sto/R2019b_201902271317&quot;&gt;
  &lt;sto.Registry type=&quot;sto.Registry&quot; uuid=&quot;abd94424-c17e-41d2-83d4-c4b71b4765c0&quot;&gt;
    &lt;clocks type=&quot;sto.Timer&quot; uuid=&quot;9e036aed-68fe-4ba0-8253-c722f826a98d&quot;&gt;
      &lt;needsToProvideTimeDuringExecution&gt;true&lt;/needsToProvideTimeDuringExecution&gt;
      &lt;clockTickConstraint&gt;PeriodicWithFixedResolution&lt;/clockTickConstraint&gt;
      &lt;resolution&gt;0.20000000000000001&lt;/resolution&gt;
      &lt;specifiedTaskingMode&gt;ClassicMultiTasking&lt;/specifiedTaskingMode&gt;
      &lt;timeAdvanceMode&gt;FixedStep&lt;/timeAdvanceMode&gt;
      &lt;clockDomain type=&quot;sto.ClockDomain&quot; uuid=&quot;d68c084c-5011-473d-8c0a-be4b697b98a7&quot;&gt;
        &lt;baseTaskID&gt;_task0&lt;/baseTaskID&gt;
        &lt;computedFundamentalStepSize&gt;0.20000000000000001&lt;/computedFundamentalStepSize&gt;
        &lt;rates type=&quot;sto.Rate&quot; uuid=&quot;78050fb9-6bbc-42ca-9853-daa2fd9fd2d2&quot;/&gt;
        &lt;rootTaskHierarchyElements type=&quot;sto.Task&quot; uuid=&quot;2df7e3e6-120f-4dce-9f02-8b82967a7bf8&quot;&gt;
          &lt;isExecutable&gt;true&lt;/isExecutable&gt;
          &lt;orderIndex&gt;1&lt;/orderIndex&gt;
          &lt;rates type=&quot;sto.Rate&quot; uuid=&quot;78050fb9-6bbc-42ca-9853-daa2fd9fd2d2&quot;&gt;
            &lt;annotation&gt;D1&lt;/annotation&gt;
            &lt;colorIndex&gt;2&lt;/colorIndex&gt;
            &lt;description&gt;Discrete 1&lt;/description&gt;
            &lt;eventSourceType&gt;UNSPECIFIED_EVENT_SOURCE&lt;/eventSourceType&gt;
            &lt;registry type=&quot;sto.Registry&quot; uuid=&quot;abd94424-c17e-41d2-83d4-c4b71b4765c0&quot;/&gt;
            &lt;taskId&gt;_task0&lt;/taskId&gt;
            &lt;rateSpec type=&quot;sto.RateSpec&quot; uuid=&quot;e159eb48-84cc-4410-a9b9-65ccde940e29&quot;&gt;
              &lt;period&gt;0.20000000000000001&lt;/period&gt;
              &lt;rateType&gt;ClassicPeriodicDiscrete&lt;/rateType&gt;
            &lt;/rateSpec&gt;
          &lt;/rates&gt;
          &lt;elementType&gt;Task&lt;/elementType&gt;
          &lt;identifier&gt;_task0&lt;/identifier&gt;
          &lt;priority&gt;40&lt;/priority&gt;
        &lt;/rootTaskHierarchyElements&gt;
      &lt;/clockDomain&gt;
    &lt;/clocks&gt;
    &lt;executionSpec&gt;Undetermined&lt;/executionSpec&gt;
    &lt;taskDependencyGraph type=&quot;sto.SerializedTaskConnectionList&quot; uuid=&quot;d07270d1-d806-4333-848b-4afcc999c6c2&quot;&gt;
      &lt;taskIdentifier&gt;_task0&lt;/taskIdentifier&gt;
    &lt;/taskDependencyGraph&gt;
    &lt;taskPriorityDirection&gt;HighNumberLast&lt;/taskPriorityDirection&gt;
    &lt;taskingMode&gt;ClassicMultiTasking&lt;/taskingMode&gt;
    &lt;tasks type=&quot;sto.Task&quot; uuid=&quot;2df7e3e6-120f-4dce-9f02-8b82967a7bf8&quot;/&gt;
    &lt;timeAdvanceMode&gt;FixedStep&lt;/timeAdvanceMode&gt;
  &lt;/sto.Registry&gt;
&lt;/slexec_sto&gt;</timingAndTaskingRegistry>
    <zeroInternalMemoryAtStartupUnchecked>true</zeroInternalMemoryAtStartupUnchecked>
    <FMUBlockMap type="ModelRefInfoRepo.FMUBlockInfo" uuid="7a20ee1b-3934-4086-b563-94480ef33caf"/>
    <codeGenInfo type="ModelRefInfoRepo.CodeGenInformation" uuid="22715af8-5341-4aca-b8d6-17dfe3d1931f"/>
    <configSettingsForConsistencyChecks type="ModelRefInfoRepo.ConfigSettingsForConsistencyChecks" uuid="f44b4254-555b-44c8-a774-458f0c84c750">
      <concurrentTaskSupport>true</concurrentTaskSupport>
      <consistentOutportInitialization>true</consistentOutportInitialization>
      <fixedStepSize>0.20000000000000001</fixedStepSize>
      <frameDiagnosticSetting>2</frameDiagnosticSetting>
      <signalLoggingSaveFormat>2</signalLoggingSaveFormat>
      <solverName>FixedStepDiscrete</solverName>
      <solverType>SOLVER_TYPE_FIXEDSTEP</solverType>
      <useDivForNetSlopComp>2</useDivForNetSlopComp>
      <hardwareSettings type="ModelRefInfoRepo.HardwareSettings" uuid="14142cae-a1bb-4352-8197-70f0e67dfbfd">
        <prodBitPerChar>8</prodBitPerChar>
        <prodBitPerDouble>64</prodBitPerDouble>
        <prodBitPerFloat>32</prodBitPerFloat>
        <prodBitPerInt>32</prodBitPerInt>
        <prodBitPerLong>32</prodBitPerLong>
        <prodBitPerLongLong>64</prodBitPerLongLong>
        <prodBitPerPointer>32</prodBitPerPointer>
        <prodBitPerPtrDiffT>32</prodBitPerPtrDiffT>
        <prodBitPerShort>16</prodBitPerShort>
        <prodBitPerSizeT>32</prodBitPerSizeT>
        <prodEndianess>1</prodEndianess>
        <prodLargestAtomicFloat>2</prodLargestAtomicFloat>
        <prodLongLongMode>true</prodLongLongMode>
        <prodShiftRight>true</prodShiftRight>
        <prodWordSize>32</prodWordSize>
      </hardwareSettings>
    </configSettingsForConsistencyChecks>
    <controllableInputRatesMap type="ModelRefInfoRepo.VarTsUIDMap" uuid="77688514-6e67-4919-9834-191dbc6e620b"/>
    <controllableOutputRatesMap type="ModelRefInfoRepo.VarTsUIDMap" uuid="eb88f5b6-4169-4e24-a6fc-578cfb6a8c16"/>
    <dataPortGroup type="ModelRefInfoRepo.DataPortGroup" uuid="2db750d0-5e9d-401e-883d-122c07d030e9"/>
    <interfaceParameterInfo type="ModelRefInfoRepo.InterfaceParameterInfo" uuid="ff6b28e8-072a-42ab-911d-0fe96d2146e4"/>
    <messageInfo type="ModelRefInfoRepo.MessageInformation" uuid="cb81005e-76f5-4cc2-a97b-3d5d29b30589"/>
    <methodInfo type="ModelRefInfoRepo.MethodExistenceInfo" uuid="b83e6ee4-35b8-499b-b657-efefddfc952c">
      <hasSystemInitializeMethod>true</hasSystemInitializeMethod>
      <hasTerminateMethod>true</hasTerminateMethod>
    </methodInfo>
    <periodicEventPortUnsupportedBlockInfo type="ModelRefInfoRepo.PeriodicEventPortUnsupportedBlockInfo" uuid="5d0a3fd9-e564-4e21-af4f-9bb8faa54b8b"/>
    <portGroupsRequireSameRate type="ModelRefInfoRepo.PortGroupsRequireSameRate" uuid="8c2dd37a-ba5a-4eef-acc5-49567535a7b4">
      <DSMPortGroups type="ModelRefInfoRepo.NameToPortGroupIdxVectMap" uuid="f3a4c87b-00c5-496e-8cea-71e3f2ab53b9"/>
      <GlobalDSMPortGroups type="ModelRefInfoRepo.NameToPortGroupIdxVectMap" uuid="94bdacfd-a543-4275-8294-09e162e2aca4"/>
      <mergedPortGroups type="ModelRefInfoRepo.NameToPortGroupIdxVectMap" uuid="b228fbff-0ceb-4a9d-ad5f-7df8a6a8b4a5"/>
    </portGroupsRequireSameRate>
    <rateSpecOfGlobalDSMAccessedByDescExpFcnMdlMap type="ModelRefInfoRepo.GlobalDSMRateSpecMap" uuid="1987619b-3242-4e47-9b3c-59f51eebc7c8"/>
    <simulinkFunctions type="ModelRefInfoRepo.SimulinkFunctions" uuid="43258471-dbb0-41b4-9010-dd46dea8262e">
      <compSimulinkFunctionCatalog></compSimulinkFunctionCatalog>
      <variantSimulinkFunctions type="ModelRefInfoRepo.VariantSimulinkFunctions" uuid="e1aca8e8-fa53-487c-99ef-089568ede088"/>
    </simulinkFunctions>
    <stateWriterToOwnerMap type="ModelRefInfoRepo.StateWriterInfo" uuid="68a47156-e1a6-476e-b068-3d696d028750"/>
    <stoClientDataRegistry type="sto.ClientDataRegistry" uuid="cbb8d035-e010-4b7c-8ec1-0b52eeedd266">
      <dataSets type="sto.ClientClockNamedDataSet" uuid="93bcd637-016c-4c10-bdc6-aaea1b54dd23">
        <tag>sltpEvents</tag>
      </dataSets>
      <dataSets type="sto.ClientTaskHierarchyElementNamedDataSet" uuid="edd38cff-1527-4387-8835-da691f5c9655">
        <tag>sltpTaskGroups</tag>
      </dataSets>
      <dataSets type="sto.ClientTaskHierarchyElementNamedDataSet" uuid="02431dc1-3c76-4891-a51e-d006ffe7ff6f">
        <dSet type="ModelRefInfoRepo.SltpTaskData" uuid="6aabdd87-e4a3-44ab-b539-b5405c3c568e"/>
        <tSet type="ModelRefInfoRepo.SltpTaskData" uuid="6aabdd87-e4a3-44ab-b539-b5405c3c568e">
          <dataName>D1</dataName>
          <linkedSet type="sto.ClientTaskHierarchyElementNamedDataSet" uuid="02431dc1-3c76-4891-a51e-d006ffe7ff6f"/>
          <id type="sto.TaskHierarchyElementId">
            <id>_task0</id>
          </id>
        </tSet>
        <tag>sltpTasks</tag>
      </dataSets>
    </stoClientDataRegistry>
    <varTsUIDMap type="ModelRefInfoRepo.VarTsUIDMap" uuid="4a1d45e2-3525-431b-8a63-d06f17fd034f"/>
  </ModelRefInfoRepo.ModelRefInfoRoot>
</MF0>